{
  "title-BecomeaSuporter": "Torne-se um apoiador",
  "title-BecomeaPartner": "Torne-se um parceiro",
  "sub-header": "Sua ajuda é importante para nós, por favor preencha seus dados e entraremos em contato o mais breve possível.",
  "button": "Enviar",
  "inputname": "*Nome",
  "inputemail": "*Correio eletrônico",
  "inputcompany": "Corporação",
  "inputmessage": "*Comunicação",
  "inputstory": "*Compartilhe conosco sua história",
  "inputupLoadyourPicture": "*Emenvie sua foto",
  "back": "Para trás"
}
